zmp_notion_exporter/__init__.py
zmp_notion_exporter/cli.py
zmp_notion_exporter/node.py
zmp_notion_exporter/notion/__init__.py
zmp_notion_exporter/notion/base.py
zmp_notion_exporter/notion/objects.py
zmp_notion_exporter/notion/threadpool_executor.py
zmp_notion_exporter/page_exporter.py
zmp_notion_exporter/utility.py
zmp_notion_exporter-0.3.8.dist-info/LICENSE
zmp_notion_exporter-0.3.8.dist-info/METADATA
zmp_notion_exporter-0.3.8.dist-info/WHEEL
zmp_notion_exporter-0.3.8.dist-info/entry_points.txt
zmp_notion_exporter-0.3.8.dist-info/RECORD
