Metadata-Version: 2.3
Name: zmp-notion-exporter
Version: 0.3.8
Summary: This is the utility library to export the markdown, html and pdf files from the notion pages
License: MIT
Author: Kilsoo Kang
Author-email: kilsoo75@gmail.com
Requires-Python: >=3.11,<4.0
Classifier: License :: OSI Approved :: MIT License
Classifier: Programming Language :: Python :: 3
Classifier: Programming Language :: Python :: 3.11
Classifier: Programming Language :: Python :: 3.12
Classifier: Programming Language :: Python :: 3.13
Requires-Dist: colorlog (>=6.9.0,<7.0.0)
Requires-Dist: notion-client (>=2.3.0,<3.0.0)
Requires-Dist: pdfkit (>=1.0.0,<2.0.0)
Requires-Dist: pydantic (>=2.10.6,<3.0.0)
Requires-Dist: python-dotenv (>=1.0.1,<2.0.0)
Requires-Dist: requests (>=2.32.3,<3.0.0)
Project-URL: Homepage, https://github.com/cloudz-mp
Project-URL: Repository, https://github.com/cloudz-mp/zmp-notion-exporter
